<annotation>
	<folder></folder>
	<filename>Video-02-12-2020--13-01-02_mov-5_jpg.rf.4f737dba4a8d716902572c0ca02a919a.jpg</filename>
	<path>Video-02-12-2020--13-01-02_mov-5_jpg.rf.4f737dba4a8d716902572c0ca02a919a.jpg</path>
	<source>
		<database>roboflow.ai</database>
	</source>
	<size>
		<width>416</width>
		<height>416</height>
		<depth>3</depth>
	</size>
	<segmented>0</segmented>
	<object>
		<name>vertical_damage</name>
		<pose>Unspecified</pose>
		<truncated>0</truncated>
		<difficult>0</difficult>
		<occluded>0</occluded>
		<bndbox>
			<xmin>24</xmin>
			<xmax>93</xmax>
			<ymin>138</ymin>
			<ymax>265</ymax>
		</bndbox>
	</object>
</annotation>
