<annotation>
	<folder></folder>
	<filename>Video-17-11-2020--15-11-50_mov-136_jpg.rf.4538344e4858283116074caca881dca9.jpg</filename>
	<path>Video-17-11-2020--15-11-50_mov-136_jpg.rf.4538344e4858283116074caca881dca9.jpg</path>
	<source>
		<database>roboflow.ai</database>
	</source>
	<size>
		<width>416</width>
		<height>416</height>
		<depth>3</depth>
	</size>
	<segmented>0</segmented>
	<object>
		<name>vertical_damage</name>
		<pose>Unspecified</pose>
		<truncated>0</truncated>
		<difficult>0</difficult>
		<occluded>0</occluded>
		<bndbox>
			<xmin>56</xmin>
			<xmax>76</xmax>
			<ymin>228</ymin>
			<ymax>255</ymax>
		</bndbox>
	</object>
</annotation>
