<annotation>
	<folder></folder>
	<filename>Video-02-12-2020--13-01-02_mov-15_jpg.rf.90b4d2c2d8444dda725bf76afac62675.jpg</filename>
	<path>Video-02-12-2020--13-01-02_mov-15_jpg.rf.90b4d2c2d8444dda725bf76afac62675.jpg</path>
	<source>
		<database>roboflow.ai</database>
	</source>
	<size>
		<width>416</width>
		<height>416</height>
		<depth>3</depth>
	</size>
	<segmented>0</segmented>
	<object>
		<name>vertical_damage</name>
		<pose>Unspecified</pose>
		<truncated>0</truncated>
		<difficult>0</difficult>
		<occluded>0</occluded>
		<bndbox>
			<xmin>285</xmin>
			<xmax>341</xmax>
			<ymin>196</ymin>
			<ymax>248</ymax>
		</bndbox>
	</object>
</annotation>
