<annotation>
	<folder></folder>
	<filename>Video-02-12-2020--13-01-02_mov-0_jpg.rf.eee9d9141efa467212e4cd9d2ed2c37c.jpg</filename>
	<path>Video-02-12-2020--13-01-02_mov-0_jpg.rf.eee9d9141efa467212e4cd9d2ed2c37c.jpg</path>
	<source>
		<database>roboflow.ai</database>
	</source>
	<size>
		<width>416</width>
		<height>416</height>
		<depth>3</depth>
	</size>
	<segmented>0</segmented>
	<object>
		<name>vertical_damage</name>
		<pose>Unspecified</pose>
		<truncated>0</truncated>
		<difficult>0</difficult>
		<occluded>0</occluded>
		<bndbox>
			<xmin>32</xmin>
			<xmax>87</xmax>
			<ymin>129</ymin>
			<ymax>203</ymax>
		</bndbox>
	</object>
</annotation>
