<annotation>
	<folder></folder>
	<filename>output_0012_jpg.rf.22e14a852c9d4c307602300eec6195c3.jpg</filename>
	<path>output_0012_jpg.rf.22e14a852c9d4c307602300eec6195c3.jpg</path>
	<source>
		<database>roboflow.ai</database>
	</source>
	<size>
		<width>416</width>
		<height>416</height>
		<depth>3</depth>
	</size>
	<segmented>0</segmented>
	<object>
		<name>vertical_damage</name>
		<pose>Unspecified</pose>
		<truncated>0</truncated>
		<difficult>0</difficult>
		<occluded>0</occluded>
		<bndbox>
			<xmin>1</xmin>
			<xmax>22</xmax>
			<ymin>215</ymin>
			<ymax>247</ymax>
		</bndbox>
	</object>
</annotation>
