<annotation>
	<folder></folder>
	<filename>Video-02-12-2020--13-02-31_mov-17_jpg.rf.65baf31d877394ec8f5a29b226b97d07.jpg</filename>
	<path>Video-02-12-2020--13-02-31_mov-17_jpg.rf.65baf31d877394ec8f5a29b226b97d07.jpg</path>
	<source>
		<database>roboflow.ai</database>
	</source>
	<size>
		<width>416</width>
		<height>416</height>
		<depth>3</depth>
	</size>
	<segmented>0</segmented>
	<object>
		<name>vertical_damage</name>
		<pose>Unspecified</pose>
		<truncated>0</truncated>
		<difficult>0</difficult>
		<occluded>0</occluded>
		<bndbox>
			<xmin>47</xmin>
			<xmax>94</xmax>
			<ymin>260</ymin>
			<ymax>305</ymax>
		</bndbox>
	</object>
</annotation>
