<annotation>
	<folder></folder>
	<filename>Video-02-12-2020--13-01-02_mov-7_jpg.rf.6477829093ed90f68dd6a86f19c9caa4.jpg</filename>
	<path>Video-02-12-2020--13-01-02_mov-7_jpg.rf.6477829093ed90f68dd6a86f19c9caa4.jpg</path>
	<source>
		<database>roboflow.ai</database>
	</source>
	<size>
		<width>416</width>
		<height>416</height>
		<depth>3</depth>
	</size>
	<segmented>0</segmented>
	<object>
		<name>vertical_damage</name>
		<pose>Unspecified</pose>
		<truncated>0</truncated>
		<difficult>0</difficult>
		<occluded>0</occluded>
		<bndbox>
			<xmin>1</xmin>
			<xmax>42</xmax>
			<ymin>139</ymin>
			<ymax>342</ymax>
		</bndbox>
	</object>
</annotation>
