<annotation>
	<folder></folder>
	<filename>Video-02-12-2020--13-03-38_mov-33_jpg.rf.7f71d667f9d0f3ba34d7953af1df6b3d.jpg</filename>
	<path>Video-02-12-2020--13-03-38_mov-33_jpg.rf.7f71d667f9d0f3ba34d7953af1df6b3d.jpg</path>
	<source>
		<database>roboflow.ai</database>
	</source>
	<size>
		<width>416</width>
		<height>416</height>
		<depth>3</depth>
	</size>
	<segmented>0</segmented>
	<object>
		<name>vertical_damage</name>
		<pose>Unspecified</pose>
		<truncated>0</truncated>
		<difficult>0</difficult>
		<occluded>0</occluded>
		<bndbox>
			<xmin>238</xmin>
			<xmax>327</xmax>
			<ymin>150</ymin>
			<ymax>272</ymax>
		</bndbox>
	</object>
</annotation>
